hashkey/__init__.py
hashkey/ccxt/__init__.py
hashkey/ccxt/hashkey.py
hashkey/ccxt/abstract/hashkey.py
hashkey/ccxt/async_support/__init__.py
hashkey/ccxt/async_support/hashkey.py
hashkey/ccxt/async_support/base/__init__.py
hashkey/ccxt/async_support/base/exchange.py
hashkey/ccxt/async_support/base/throttler.py
hashkey/ccxt/async_support/base/ws/__init__.py
hashkey/ccxt/async_support/base/ws/aiohttp_client.py
hashkey/ccxt/async_support/base/ws/cache.py
hashkey/ccxt/async_support/base/ws/client.py
hashkey/ccxt/async_support/base/ws/fast_client.py
hashkey/ccxt/async_support/base/ws/functions.py
hashkey/ccxt/async_support/base/ws/future.py
hashkey/ccxt/async_support/base/ws/order_book.py
hashkey/ccxt/async_support/base/ws/order_book_side.py
hashkey/ccxt/base/__init__.py
hashkey/ccxt/base/decimal_to_precision.py
hashkey/ccxt/base/errors.py
hashkey/ccxt/base/exchange.py
hashkey/ccxt/base/precise.py
hashkey/ccxt/base/types.py
hashkey/ccxt/pro/__init__.py
hashkey/ccxt/pro/hashkey.py
hashkey/ccxt/static_dependencies/README.md
hashkey/ccxt/static_dependencies/__init__.py
hashkey/ccxt/static_dependencies/ecdsa/__init__.py
hashkey/ccxt/static_dependencies/ecdsa/_version.py
hashkey/ccxt/static_dependencies/ecdsa/curves.py
hashkey/ccxt/static_dependencies/ecdsa/der.py
hashkey/ccxt/static_dependencies/ecdsa/ecdsa.py
hashkey/ccxt/static_dependencies/ecdsa/ellipticcurve.py
hashkey/ccxt/static_dependencies/ecdsa/keys.py
hashkey/ccxt/static_dependencies/ecdsa/numbertheory.py
hashkey/ccxt/static_dependencies/ecdsa/rfc6979.py
hashkey/ccxt/static_dependencies/ecdsa/util.py
hashkey/ccxt/static_dependencies/ethereum/__init__.py
hashkey/ccxt/static_dependencies/ethereum/abi/__init__.py
hashkey/ccxt/static_dependencies/ethereum/abi/abi.py
hashkey/ccxt/static_dependencies/ethereum/abi/base.py
hashkey/ccxt/static_dependencies/ethereum/abi/codec.py
hashkey/ccxt/static_dependencies/ethereum/abi/constants.py
hashkey/ccxt/static_dependencies/ethereum/abi/decoding.py
hashkey-0.0.17.dist-info/METADATA
hashkey-0.0.17.dist-info/WHEEL
hashkey-0.0.17.dist-info/RECORD
